simlib/__init__.py
simlib/_version.py
simlib/analysis/__init__.py
simlib/analysis/protein.py
simlib/geometry/__init__.py
simlib/io/__init__.py
simlib/io/errata.py
simlib/misc/__init__.py
simlib/misc/types.py
simlib-0.0.0.dist-info/LICENSE.md
simlib-0.0.0.dist-info/METADATA
simlib-0.0.0.dist-info/WHEEL
simlib-0.0.0.dist-info/top_level.txt
simlib-0.0.0.dist-info/zip-safe
simlib-0.0.0.dist-info/RECORD
